owlmixin/__init__.py
owlmixin/errors.py
owlmixin/owlcollections.py
owlmixin/owlenum.py
owlmixin/owloption.py
owlmixin/samples.py
owlmixin/transformers.py
owlmixin/util.py
owlmixin-7.0.1.dist-info/METADATA
owlmixin-7.0.1.dist-info/WHEEL
owlmixin-7.0.1.dist-info/licenses/LICENSE
owlmixin-7.0.1.dist-info/RECORD
