Metadata-Version: 2.4
Name: owlmixin
Version: 7.0.1
Summary: Mixin which converts ``data class instance`` and others each other more simple.
Project-URL: homepage, https://github.com/tadashi-aikawa/owlmixin
Project-URL: repository, https://github.com/tadashi-aikawa/owlmixin
Project-URL: documentation, https://tadashi-aikawa.github.io/owlmixin/
Author-email: tadashi-aikawa <syou.maman@gmail.com>
License: MIT
License-File: LICENSE
Keywords: dict,json,mixin,parser,yaml
Classifier: Development Status :: 5 - Production/Stable
Classifier: Intended Audience :: Developers
Classifier: Topic :: Software Development :: Libraries :: Python Modules
Classifier: Topic :: Utilities
Requires-Python: <4.0,>=3.9
Requires-Dist: pyyaml<7.0,>=6.0
